aiexec/__init__.py
aiexec/executor.py
aiexec/loop.py
aiexec/main.py
aiexec/model.py
aiexec/parser.py
aiexec/templates.py
aiexec-0.1.0.dist-info/METADATA
aiexec-0.1.0.dist-info/WHEEL
aiexec-0.1.0.dist-info/entry_points.txt
aiexec-0.1.0.dist-info/top_level.txt
aiexec-0.1.0.dist-info/RECORD
