Metadata-Version: 2.4
Name: aiexec
Version: 0.1.0
Summary: Run .ai natural-language automation scripts in a safe terminal loop.
Requires-Python: >=3.10
Requires-Dist: typer>=0.12.3
Requires-Dist: pyyaml>=6.0.2
Requires-Dist: rich>=13.7.1
